[
    {
        "uuid": "ae13b1ed-6799-4105-804a-e196c5f9a12c",
        "stock": "SMCI",
        "time": "2024-08-19T18:11:25.029206-04:00",
        "price": 621.6999999999999,
        "share": 0.0,
        "remain_portion": 4
    },
    {
        "uuid": "d3e61cbc-ebab-46f8-894b-aefed48aaf43",
        "stock": "SMCI",
        "time": "2024-08-19T19:21:30.442458-04:00",
        "price": 621.06,
        "share": 1.0,
        "remain_portion": 2
    },
    {
        "uuid": "9c292835-d87b-448e-b6a7-1d210ab6fded",
        "stock": "SMCI",
        "time": "2024-08-19T19:35:47.857452-04:00",
        "price": 621.06,
        "share": 0.0,
        "remain_portion": 1
    },
    {
        "uuid": "523f50f8-2747-425b-853b-fdf99117e301",
        "stock": "SMCI",
        "time": "2024-08-19T19:51:05.148600-04:00",
        "price": 621.06,
        "share": 2.0,
        "remain_portion": 0
    }
]